[
  {
    "id": 1,
    "name": "Tamma",
    "lastName": "Amy",
    "phone": "182 417 4716",
    "email": "tamy0@ehow.com",
    "password": "Onqe4lrrtIK"
  },
  {
    "id": 2,
    "name": "Rogers",
    "lastName": "Audibert",
    "phone": "716 270 1006",
    "email": "raudibert1@nifty.com",
    "password": "BeN6qfHZzZQ"
  },
  {
    "id": 3,
    "name": "Leyla",
    "lastName": "Summerson",
    "phone": "166 334 2551",
    "email": "lsummerson2@indiegogo.com",
    "password": "6U06FdP"
  },
  {
    "id": 4,
    "name": "Tove",
    "lastName": "Lutwyche",
    "phone": "692 503 1656",
    "email": "tlutwyche3@bbc.co.uk",
    "password": "vx7e37p37RWe"
  },
  {
    "id": 5,
    "name": "Huntlee",
    "lastName": "Odegaard",
    "phone": "305 149 6573",
    "email": "hodegaard4@scientificamerican.com",
    "password": "FYt7TaVOTc"
  },
  {
    "id": 6,
    "name": "Lyssa",
    "lastName": "Densie",
    "phone": "226 176 8298",
    "email": "ldensie5@state.tx.us",
    "password": "4WDGkJ5F"
  },
  {
    "id": 7,
    "name": "Armin",
    "lastName": "Discombe",
    "phone": "447 981 6048",
    "email": "adiscombe6@java.com",
    "password": "7P2fIV"
  },
  {
    "id": 8,
    "name": "Norris",
    "lastName": "Jellings",
    "phone": "171 284 1887",
    "email": "njellings7@gizmodo.com",
    "password": "TSH2brh"
  },
  {
    "id": 9,
    "name": "Byrom",
    "lastName": "Blackstone",
    "phone": "485 198 1280",
    "email": "bblackstone8@canalblog.com",
    "password": "iniN6OfE"
  },
  {
    "id": 10,
    "name": "Carri",
    "lastName": "Loveday",
    "phone": "792 989 6029",
    "email": "cloveday9@sciencedirect.com",
    "password": "6RNUWIDD"
  }
]